README.md
setup.py
pytrails/__init__.py
pytrails.egg-info/PKG-INFO
pytrails.egg-info/SOURCES.txt
pytrails.egg-info/dependency_links.txt
pytrails.egg-info/top_level.txt
pytrails/h5trails/__init__.py
pytrails/h5trails/markovchain.py
pytrails/h5trails/test_markovchain.py
pytrails/hyptrails/__init__.py
pytrails/hyptrails/markovchain.py
pytrails/hyptrails/markovchain_variants.py
pytrails/mixedtrails/__init__.py
pytrails/mixedtrails/mtmc.py
pytrails/sparktrails/__init__.py
pytrails/sparktrails/livehypotheses.py
pytrails/sparktrails/markovchain.py
pytrails/sparktrails/matrixutils.py
pytrails/sparktrails/test_markovchain.py
pytrails/sparktrails/test_matrixutils.py