Metadata-Version: 1.0
Name: pytrails
Version: 0.0.3
Summary: A collection of Bayesian methods for hypothesis comparison on sequential data.
Home-page: https://github.com/mgbckr/pytrails
Author: Martin Becker
Author-email: becker@informatik.uni-wuerzburg.de
License: UNKNOWN
Keywords: bayesian model comparison bayes factor Markov model sequence sequential data
Platform: UNKNOWN
